novajoin_tempest_plugin/README.rst
novajoin_tempest_plugin/__init__.py
novajoin_tempest_plugin/clients.py
novajoin_tempest_plugin/config.py
novajoin_tempest_plugin/plugin.py
novajoin_tempest_plugin/ipa/__init__.py
novajoin_tempest_plugin/ipa/ipa_client.py
novajoin_tempest_plugin/tests/__init__.py
novajoin_tempest_plugin/tests/base.py
novajoin_tempest_plugin/tests/test_novajoin_tempest_plugin.py
novajoin_tempest_plugin/tests/api/__init__.py
novajoin_tempest_plugin/tests/scenario/__init__.py
novajoin_tempest_plugin/tests/scenario/manager.py
novajoin_tempest_plugin/tests/scenario/novajoin_manager.py
novajoin_tempest_plugin/tests/scenario/test_novajoin_enrollment.py
novajoin_tempest_plugin/tests/scenario/test_tripleo_deployment.py
novajoin_tempest_plugin/tests/scenario/test_tripleo_tls.py
novajoin_tempest_plugin-0.0.3.dist-info/DESCRIPTION.rst
novajoin_tempest_plugin-0.0.3.dist-info/METADATA
novajoin_tempest_plugin-0.0.3.dist-info/RECORD
novajoin_tempest_plugin-0.0.3.dist-info/WHEEL
novajoin_tempest_plugin-0.0.3.dist-info/entry_points.txt
novajoin_tempest_plugin-0.0.3.dist-info/metadata.json
novajoin_tempest_plugin-0.0.3.dist-info/pbr.json
novajoin_tempest_plugin-0.0.3.dist-info/top_level.txt
