Metadata-Version: 2.0
Name: novajoin-tempest-plugin
Version: 0.0.3
Summary: OpenStack Novajoin tempest tests.
Home-page: http://www.openstack.org/
Author: OpenStack
Author-email: openstack-dev@lists.openstack.org
License: UNKNOWN
Platform: UNKNOWN
Classifier: Environment :: OpenStack
Classifier: Intended Audience :: Information Technology
Classifier: Intended Audience :: System Administrators
Classifier: License :: OSI Approved :: Apache Software License
Classifier: Operating System :: POSIX :: Linux
Classifier: Programming Language :: Python
Classifier: Programming Language :: Python :: 2
Classifier: Programming Language :: Python :: 2.7
Classifier: Programming Language :: Python :: 3
Classifier: Programming Language :: Python :: 3.3
Classifier: Programming Language :: Python :: 3.5
Requires-Dist: oslo.config (>=3.22.0)
Requires-Dist: pbr (>=1.8)
Requires-Dist: tempest (>=12.1.0)
